MANIFEST.in
VERSION
setup.py
dwolla/__init__.py
dwolla/version.py
dwolla/test/__init__.py
dwolla/test/test_dwolla.py
pydwolla.egg-info/PKG-INFO
pydwolla.egg-info/SOURCES.txt
pydwolla.egg-info/dependency_links.txt
pydwolla.egg-info/requires.txt
pydwolla.egg-info/top_level.txt