Metadata-Version: 1.0
Name: pydwolla
Version: 0.1.0
Summary: An elegant Dwolla python wrapper
Home-page: https://github.com/roycehaynes/pydwolla
Author: Royce Haynes
Author-email: royce.haynes@gmail.com
License: MIT
Platform: UNKNOWN
